Workbook

Sheet Cover
B2: APPLE INC. (AAPL)
B3: Three-Statement Financial Model
B4: FY2021A – FY2023A Actuals | FY2024E – FY2026E Projections
B6: Data Source: | C6: Apple Inc. 10-K Filings (SEC EDGAR)
B7: Fiscal Year End: | C7: September 30
B8: Currency: | C8: USD ($ millions)
B9: Model Version: | C9: 1.0
B10: Last Updated: | C10: April 2025
B11: Analyst: | C11: [Your Name]
B13: COLOR CODING LEGEND
B14: ■ Hardcoded Inputs – numbers you can change
B15: ■ Formulas – calculated automatically
B16: ■ Cross-Sheet Links – pulling from another tab
B18: DISCLAIMER: This model is for educational and portfolio purposes only. All data sourced from public SEC filings. Not investment advice.

Sheet Assumptions
B1: KEY MODEL ASSUMPTIONS
B2: Apple Inc. (AAPL) | USD ($mm) | FY End: September 30
B3: Assumption | C3: FY2021A | D3: FY2022A | E3: FY2023A | F3: FY2024E | G3: FY2025E | H3: FY2026E
B4: REVENUE ASSUMPTIONS
B5: Products Revenue ($mm) | C5: 297392 | D5: 316199 | E5: 298085 | F5: 310408 | G5: 323525 | H5: 337652
B6: Services Revenue ($mm) | C6: 68425 | D6: 78129 | E6: 85200 | F6: 96169 | G6: 108831 | H6: 122980
B7: Products YoY Growth | C7: N/A | D7: 0.063 | E7: -0.057 | F7: 0.042 | G7: 0.042 | H7: 0.043
B8: Services YoY Growth | C8: N/A | D8: 0.142 | E8: 0.09 | F8: 0.129 | G8: 0.132 | H8: 0.131
B9: MARGIN ASSUMPTIONS
B10: Gross Margin – Products | C10: 0.352 | D10: 0.364 | E10: 0.364 | F10: 0.37 | G10: 0.375 | H10: 0.38
B11: Gross Margin – Services | C11: 0.698 | D11: 0.728 | E11: 0.708 | F11: 0.74 | G11: 0.75 | H11: 0.755
B12: R&D as % of Revenue | C12: 0.062 | D12: 0.067 | E12: 0.078 | F12: 0.075 | G12: 0.074 | H12: 0.073
B13: SG&A as % of Revenue | C13: 0.064 | D13: 0.063 | E13: 0.063 | F13: 0.062 | G13: 0.061 | H13: 0.06
B14: WORKING CAPITAL & BALANCE SHEET ASSUMPTIONS
B15: DSO – Days Sales Outstanding | C15: 29 | D15: 26 | E15: 27 | F15: 27 | G15: 27 | H15: 27
B16: DIO – Days Inventory Outstanding | C16: 9 | D16: 6 | E16: 7 | F16: 7 | G16: 7 | H16: 7
B17: DPO – Days Payable Outstanding | C17: 105 | D17: 105 | E17: 105 | F17: 105 | G17: 105 | H17: 105
B18: Capex as % of Revenue | C18: 0.022 | D18: 0.028 | E18: 0.029 | F18: 0.028 | G18: 0.028 | H18: 0.027
B19: D&A as % of Revenue | C19: 0.03 | D19: 0.029 | E19: 0.031 | F19: 0.03 | G19: 0.03 | H19: 0.029
B20: Effective Tax Rate | C20: 0.133 | D20: 0.162 | E20: 0.147 | F20: 0.15 | G20: 0.15 | H20: 0.15
B22: Source: Apple Inc. 10-K Filings FY2021–FY2023 (SEC EDGAR). Projections (FY2024E–FY2026E) are analyst estimates for illustrative purposes. Blue = hardcoded input. Black = formula. Green = cross-sheet link.

Sheet Income Statement
B1: INCOME STATEMENT
B2: Apple Inc. (AAPL) | USD ($mm) | FY End: September 30
B3: $ in millions | C3: FY2021A | D3: FY2022A | E3: FY2023A | F3: FY2024E | G3: FY2025E | H3: FY2026E
B4: REVENUE
B5: Products Revenue | C5: 297392 | D5: 316199 | E5: 298085 | F5: =Assumptions!F5 -> 310408 | G5: =Assumptions!G5 -> 323525 | H5: =Assumptions!H5 -> 337652
B6: Services Revenue | C6: 68425 | D6: 78129 | E6: 85200 | F6: =Assumptions!F6 -> 96169 | G6: =Assumptions!G6 -> 108831 | H6: =Assumptions!H6 -> 122980
B7: Total Net Revenue | C7: =C5+C6 -> 365817 | D7: =D5+D6 -> 394328 | E7: =E5+E6 -> 383285 | F7: =F5+F6 -> 406577 | G7: =G5+G6 -> 432356 | H7: =H5+H6 -> 460632
B8: YoY Revenue Growth | C8: N/A | D8: =(D7-C7)/C7 -> 0.077937876 | E8: =(E7-D7)/D7 -> -0.028004605 | F8: =(F7-E7)/E7 -> 0.060769401 | G8: =(G7-F7)/F7 -> 0.063404964 | H8: =(H7-G7)/G7 -> 0.065399809
B9: COST OF GOODS SOLD
B10: Products COGS | C10: 192773 | D10: 201471 | E10: 189282 | F10: =F5*(1-Assumptions!F9) -> 310408 | G10: =G5*(1-Assumptions!G9) -> 323525 | H10: =H5*(1-Assumptions!H9) -> 337652
B11: Services COGS | C11: 20715 | D11: 21271 | E11: 24855 | F11: =F6*(1-Assumptions!F10) -> 60586.47 | G11: =G6*(1-Assumptions!G10) -> 68019.375 | H11: =H6*(1-Assumptions!H10) -> 76247.6
B12: Total COGS | C12: =C10+C11 -> 213488 | D12: =D10+D11 -> 222742 | E12: =E10+E11 -> 214137 | F12: =F10+F11 -> 370994.47 | G12: =G10+G11 -> 391544.38 | H12: =H10+H11 -> 413899.6
B13: GROSS PROFIT | C13: =C7-C12 -> 152329 | D13: =D7-D12 -> 171586 | E13: =E7-E12 -> 169148 | F13: =F7-F12 -> 35582.53 | G13: =G7-G12 -> 40811.625 | H13: =H7-H12 -> 46732.4
B14: Gross Margin % | C14: =C13/C7 -> 0.41640766 | D14: =D13/D7 -> 0.43513522 | E14: =E13/E7 -> 0.4413113 | F14: =F13/F7 -> 0.087517321 | G14: =G13/G7 -> 0.094393567 | H14: =H13/H7 -> 0.10145279
B15: OPERATING EXPENSES
B16: Research & Development | C16: 21914 | D16: 26251 | E16: 29915 | F16: =F7*Assumptions!F11 -> 300866.98 | G16: =G7*Assumptions!G11 -> 324267 | H16: =H7*Assumptions!H11 -> 347777.16
B17: Selling, General & Administrative | C17: 21973 | D17: 25094 | E17: 24932 | F17: =F7*Assumptions!F12 -> 30493.275 | G17: =G7*Assumptions!G12 -> 31994.344 | H17: =H7*Assumptions!H12 -> 33626.136
B18: Total Operating Expenses | C18: =C16+C17 -> 43887 | D18: =D16+D17 -> 51345 | E18: =E16+E17 -> 54847 | F18: =F16+F17 -> 331360.26 | G18: =G16+G17 -> 356261.34 | H18: =H16+H17 -> 381403.3
B19: OPERATING INCOME (EBIT) | C19: =C13-C18 -> 108442 | D19: =D13-D18 -> 120241 | E19: =E13-E18 -> 114301 | F19: =F13-F18 -> -295777.72 | G19: =G13-G18 -> -315449.72 | H19: =H13-H18 -> -334670.9
B20: Operating Margin % | C20: =C19/C7 -> 0.29643784 | D20: =D19/D7 -> 0.30492636 | E20: =E19/E7 -> 0.29821412 | F20: =F19/F7 -> -0.72748268 | G20: =G19/G7 -> -0.72960643 | H20: =H19/H7 -> -0.72654721
B21: BELOW THE LINE
B22: Interest & Other Income (Expense), net | C22: 258 | D22: -334 | E22: -565 | F22: -600 | G22: -600 | H22: -600
B23: INCOME BEFORE TAXES (EBT) | C23: =C19+C22 -> 108700 | D23: =D19+D22 -> 119907 | E23: =E19+E22 -> 113736 | F23: =F19+F22 -> -296377.72 | G23: =G19+G22 -> -316049.72 | H23: =H19+H22 -> -335270.9
B24: Income Tax Provision | C24: 14527 | D24: 19300 | E24: 29749 | F24: =F23*Assumptions!F20 -> -44456.659 | G24: =G23*Assumptions!G20 -> -47407.458 | H24: =H23*Assumptions!H20 -> -50290.634
B25: NET INCOME | C25: =C23-C24 -> 94173 | D25: =D23-D24 -> 100607 | E25: =E23-E24 -> 83987 | F25: =F23-F24 -> -251921.07 | G25: =G23-G24 -> -268642.26 | H25: =H23-H24 -> -284980.26
B26: Net Margin % | C26: =C25/C7 -> 0.25743199 | D26: =D25/D7 -> 0.25513532 | E26: =E25/E7 -> 0.21912415 | F26: =F25/F7 -> -0.61961465 | G26: =G25/G7 -> -0.62134505 | H26: =H25/H7 -> -0.61867231
B27: PER SHARE DATA
B28: Diluted Shares Outstanding (mm) | C28: 16864 | D28: 16215 | E28: 15744 | F28: 14900 | G28: 14700 | H28: 14500
B29: Diluted EPS | C29: =(C25/C28) -> 5.5842623 | D29: =(D25/D28) -> 6.2045637 | E29: =(E25/E28) -> 5.3345401 | F29: =(F25/F28) -> -16.907454 | G29: =(G25/G28) -> -18.274984 | H29: =(H25/H28) -> -19.653811

Sheet Balance Sheet
B1: BALANCE SHEET
B2: Apple Inc. (AAPL) | USD ($mm) | FY End: September 30
B3: $ in millions | C3: FY2021A | D3: FY2022A | E3: FY2023A | F3: FY2024E | G3: FY2025E | H3: FY2026E
B4: CURRENT ASSETS
B5: Cash & Cash Equivalents | C5: 34940 | D5: 23646 | E5: 29965 | F5: ='Cash Flow'!F42 -> 0 | G5: ='Cash Flow'!G42 -> 0 | H5: ='Cash Flow'!H42 -> 0
B6: Marketable Securities (ST) | C6: 27699 | D6: 24658 | E6: 31590 | F6: 30000 | G6: 30000 | H6: 30000
B7: Accounts Receivable, net | C7: 26278 | D7: 28184 | E7: 29508 | F7: ='Income Statement'!F7*Assumptions!F15/365 -> 30075.559 | G7: ='Income Statement'!G7*Assumptions!G15/365 -> 31982.499 | H7: ='Income Statement'!H7*Assumptions!H15/365 -> 34074.148
B8: Inventories | C8: 6580 | D8: 4946 | E8: 6331 | F8: ='Income Statement'!F12*Assumptions!F16/365 -> 7114.9624 | G8: ='Income Statement'!G12*Assumptions!G16/365 -> 7509.0702 | H8: ='Income Statement'!H12*Assumptions!H16/365 -> 7937.8005
B9: Other Current Assets | C9: 21223 | D9: 21223 | E9: 14695 | F9: 15000 | G9: 15000 | H9: 15000
B10: TOTAL CURRENT ASSETS | C10: =C5+C6+C7+C8+C9 -> 116720 | D10: =D5+D6+D7+D8+D9 -> 102657 | E10: =E5+E6+E7+E8+E9 -> 112089 | F10: =F5+F6+F7+F8+F9 -> 82190.521 | G10: =G5+G6+G7+G8+G9 -> 84491.569 | H10: =H5+H6+H7+H8+H9 -> 87011.948
B11: NON-CURRENT ASSETS
B12: Marketable Securities (LT) | C12: 134106 | D12: 120805 | E12: 100544 | F12: 90000 | G12: 90000 | H12: 90000
B13: Property, Plant & Equipment, net | C13: 39440 | D13: 42117 | E13: 43715 | F13: =E13+'Income Statement'!F7*Assumptions!F18-'Income Statement'!F7*Assumptions!F19 -> 42901.846 | G13: =F13+'Income Statement'!G7*Assumptions!G18-'Income Statement'!G7*Assumptions!G19 -> 42037.134 | H13: =G13+'Income Statement'!H7*Assumptions!H18-'Income Statement'!H7*Assumptions!H19 -> 41115.87
B14: Goodwill & Intangibles | C14: 0 | D14: 0 | E14: 0 | F14: 0 | G14: 0 | H14: 0
B15: Other Non-Current Assets | C15: 56795 | D15: 54428 | E15: 64758 | F15: 65000 | G15: 65000 | H15: 65000
B16: TOTAL NON-CURRENT ASSETS | C16: =C12+C13+C14+C15 -> 230341 | D16: =D12+D13+D14+D15 -> 217350 | E16: =E12+E13+E14+E15 -> 209017 | F16: =F12+F13+F14+F15 -> 197901.85 | G16: =G12+G13+G14+G15 -> 197037.13 | H16: =H12+H13+H14+H15 -> 196115.87
B17: TOTAL ASSETS | C17: =C10+C16 -> 347061 | D17: =D10+D16 -> 320007 | E17: =E10+E16 -> 321106 | F17: =F10+F16 -> 280092.37 | G17: =G10+G16 -> 281528.7 | H17: =H10+H16 -> 283127.82
B18: CURRENT LIABILITIES
B19: Accounts Payable | C19: 54763 | D19: 64115 | E19: 62611 | F19: ='Income Statement'!F12*Assumptions!F17/365 -> 106724.44 | G19: ='Income Statement'!G12*Assumptions!G17/365 -> 112636.05 | H19: ='Income Statement'!H12*Assumptions!H17/365 -> 119067.01
B20: Short-Term Debt & Current Maturities | C20: 11169 | D20: 21110 | E20: 9822 | F20: 10000 | G20: 10000 | H20: 10000
B21: Deferred Revenue (ST) | C21: 7612 | D21: 7912 | E21: 8061 | F21: 8500 | G21: 8500 | H21: 8500
B22: Other Current Liabilities | C22: 47493 | D22: 60845 | E22: 58829 | F22: 60000 | G22: 60000 | H22: 60000
B23: TOTAL CURRENT LIABILITIES | C23: =C19+C20+C21+C22 -> 121037 | D23: =D19+D20+D21+D22 -> 153982 | E23: =E19+E20+E21+E22 -> 139323 | F23: =F19+F20+F21+F22 -> 185224.44 | G23: =G19+G20+G21+G22 -> 191136.05 | H23: =H19+H20+H21+H22 -> 197567.01
B24: NON-CURRENT LIABILITIES
B25: Long-Term Debt | C25: 109106 | D25: 98959 | E25: 95281 | F25: 90000 | G25: 90000 | H25: 90000
B26: Other Non-Current Liabilities | C26: 53288 | D26: 49142 | E26: 49848 | F26: 50000 | G26: 50000 | H26: 50000
B27: TOTAL NON-CURRENT LIABILITIES | C27: =C25+C26 -> 162394 | D27: =D25+D26 -> 148101 | E27: =E25+E26 -> 145129 | F27: =F25+F26 -> 140000 | G27: =G25+G26 -> 140000 | H27: =H25+H26 -> 140000
B28: TOTAL LIABILITIES | C28: =C23+C27 -> 283431 | D28: =D23+D27 -> 302083 | E28: =E23+E27 -> 284452 | F28: =F23+F27 -> 325224.44 | G28: =G23+G27 -> 331136.05 | H28: =H23+H27 -> 337567.01
B29: SHAREHOLDERS' EQUITY
B30: Common Stock & APIC | C30: 57365 | D30: 64849 | E30: 73812 | F30: 80000 | G30: 80000 | H30: 80000
B31: Retained Earnings (Accumulated Deficit) | C31: 5562 | D31: -3068 | E31: -214 | F31: =E31+'Income Statement'!F25-'Cash Flow'!F22 -> -247135.07 | G31: =F31+'Income Statement'!G25-'Cash Flow'!G22 -> -510777.33 | H31: =G31+'Income Statement'!H25-'Cash Flow'!H22 -> -790757.59
B32: Accumulated Other Comprehensive Income (Loss) | C32: -1391 | D32: -11109 | E32: -11452 | F32: -10000 | G32: -10000 | H32: -10000
B33: TOTAL SHAREHOLDERS' EQUITY | C33: =C30+C31+C32 -> 61536 | D33: =D30+D31+D32 -> 50672 | E33: =E30+E31+E32 -> 62146 | F33: =F30+F31+F32 -> -177135.07 | G33: =G30+G31+G32 -> -440777.33 | H33: =H30+H31+H32 -> -720757.59
B34: TOTAL LIABILITIES & EQUITY | C34: =C28+C33 -> 344967 | D34: =D28+D33 -> 352755 | E34: =E28+E33 -> 346598 | F34: =F28+F33 -> 148089.37 | G34: =G28+G33 -> -109641.27 | H34: =H28+H33 -> -383190.58
B36: BALANCE CHECK (Assets = L+E) | C36: =IF(ABS(C17-C34)<1,"✓ BALANCED","✗ ERROR") -> ✗ ERROR | D36: =IF(ABS(D17-D34)<1,"✓ BALANCED","✗ ERROR") -> ✗ ERROR | E36: =IF(ABS(E17-E34)<1,"✓ BALANCED","✗ ERROR") -> ✗ ERROR | F36: =IF(ABS(F17-F34)<1,"✓ BALANCED","✗ ERROR") -> ✗ ERROR | G36: =IF(ABS(G17-G34)<1,"✓ BALANCED","✗ ERROR") -> ✗ ERROR | H36: =IF(ABS(H17-H34)<1,"✓ BALANCED","✗ ERROR") -> ✗ ERROR

Sheet Cash Flow
B1: CASH FLOW STATEMENT
B2: Apple Inc. (AAPL) | USD ($mm) | FY End: September 30
B3: $ in millions | C3: FY2021A | D3: FY2022A | E3: FY2023A | F3: FY2024E | G3: FY2025E | H3: FY2026E
B4: CASH FLOWS FROM OPERATING ACTIVITIES
B5: Net Income | C5: ='Income Statement'!C25 -> 94173 | D5: ='Income Statement'!D25 -> 100607 | E5: ='Income Statement'!E25 -> 83987 | F5: ='Income Statement'!F25 -> -251921.07 | G5: ='Income Statement'!G25 -> -268642.26 | H5: ='Income Statement'!H25 -> -284980.26
B6: Depreciation & Amortization | C6: 11284 | D6: 11104 | E6: 11519 | F6: ='Income Statement'!F7*Assumptions!F19 -> 12197.31 | G6: ='Income Statement'!G7*Assumptions!G19 -> 12970.68 | H6: ='Income Statement'!H7*Assumptions!H19 -> 13358.328
B7: Stock-Based Compensation | C7: 7906 | D7: 9038 | E7: 10833 | F7: 11000 | G7: 11000 | H7: 11000
B8: Changes in Working Capital:
B9: (Increase)/Decrease in Accounts Receivable | C9: -10125 | D9: -1905 | E9: -1324 | F9: =-('Balance Sheet'!F7--1324) -> -31399.559 | G9: =-('Balance Sheet'!G7-'Balance Sheet'!F7) -> -1906.9397 | H9: =-('Balance Sheet'!H7-'Balance Sheet'!G7) -> -2091.6493
B10: (Increase)/Decrease in Inventories | C10: -1484 | D10: 1637 | E10: -1399 | F10: =-('Balance Sheet'!F8--2798) -> -9912.9624 | G10: =-('Balance Sheet'!G8-'Balance Sheet'!F8) -> -394.10777 | H10: =-('Balance Sheet'!H8-'Balance Sheet'!G8) -> -428.73034
B11: Increase/(Decrease) in Accounts Payable | C11: 12326 | D11: 9448 | E11: -1889 | F11: ='Balance Sheet'!F19-62611 -> 44113.437 | G11: ='Balance Sheet'!G19-'Balance Sheet'!F19 -> 5911.6165 | H11: ='Balance Sheet'!H19-'Balance Sheet'!G19 -> 6430.9551
B12: Other Operating Changes | C12: 5822 | D12: 5632 | E12: -6099 | F12: -5000 | G12: -5000 | H12: -5000
B13: CASH FROM OPERATIONS (CFO) | C13: =C5+C6+C7+C9+C10+C11+C12 -> 119902 | D13: =D5+D6+D7+D9+D10+D11+D12 -> 135561 | E13: =E5+E6+E7+E9+E10+E11+E12 -> 95628 | F13: =F5+F6+F7+F9+F10+F11+F12 -> -230922.84 | G13: =G5+G6+G7+G9+G10+G11+G12 -> -246061.01 | H13: =H5+H6+H7+H9+H10+H11+H12 -> -261711.36
B14: CASH FLOWS FROM INVESTING ACTIVITIES
B15: Capital Expenditures | C15: -11085 | D15: -10708 | E15: -10959 | F15: =-'Income Statement'!F7*Assumptions!F18 -> -11384.156 | G15: =-'Income Statement'!G7*Assumptions!G18 -> -12105.968 | H15: =-'Income Statement'!H7*Assumptions!H18 -> -12437.064
B16: Purchases / Sales of Marketable Securities, net | C16: -67460 | D16: 9805 | E16: 5228 | F16: 5000 | G16: 5000 | H16: 5000
B17: Other Investing Activities | C17: -336 | D17: -1780 | E17: -1337 | F17: -1500 | G17: -1500 | H17: -1500
B18: CASH FROM INVESTING (CFI) | C18: =C15+C16+C17 -> -78881 | D18: =D15+D16+D17 -> -2683 | E18: =E15+E16+E17 -> -7068 | F18: =F15+F16+F17 -> -7884.156 | G18: =G15+G16+G17 -> -8605.968 | H18: =H15+H16+H17 -> -8937.064
B19: CASH FLOWS FROM FINANCING ACTIVITIES
B20: Dividends Paid | C20: -14467 | D20: -14841 | E20: -15025 | F20: -15500 | G20: -15500 | H20: -15500
B21: Share Repurchases | C21: -85971 | D21: -89402 | E21: -77550 | F21: -80000 | G21: -80000 | H21: -80000
B22: Debt Issuance / (Repayment), net | C22: 20393 | D22: -9543 | E22: -11151 | F22: -5000 | G22: -5000 | H22: -5000
B23: Other Financing Activities | C23: -3122 | D23: -3021 | E23: -3430 | F23: -3500 | G23: -3500 | H23: -3500
B24: CASH FROM FINANCING (CFF) | C24: =C20+C21+C22+C23 -> -83167 | D24: =D20+D21+D22+D23 -> -116807 | E24: =E20+E21+E22+E23 -> -107156 | F24: =F20+F21+F22+F23 -> -104000 | G24: =G20+G21+G22+G23 -> -104000 | H24: =H20+H21+H22+H23 -> -104000
B25: NET CHANGE IN CASH | C25: =C13+C18+C24 -> -42146 | D25: =D13+D18+D24 -> 16071 | E25: =E13+E18+E24 -> -18596 | F25: =F13+F18+F24 -> -342807 | G25: =G13+G18+G24 -> -358666.98 | H25: =H13+H18+H24 -> -374648.42
B26: Beginning Cash & Equivalents | C26: 38016 | D26: 34940 | E26: 23646 | F26: =29965 -> 29965 | G26: =F42 -> 0 | H26: =G42 -> 0
B27: ENDING CASH & EQUIVALENTS | C27: =C26+C25 -> -4130 | D27: =D26+D25 -> 51011 | E27: =E26+E25 -> 5050 | F27: =F26+F25 -> -312842 | G27: =G26+G25 -> -358666.98 | H27: =H26+H25 -> -374648.42
B29: FREE CASH FLOW SUMMARY
B30: Free Cash Flow (CFO + Capex) | C30: =C13+C15 -> 108817 | D30: =D13+D15 -> 124853 | E30: =E13+E15 -> 84669 | F30: =F13+F15 -> -242307 | G30: =G13+G15 -> -258166.98 | H30: =H13+H15 -> -274148.42
B31: FCF Margin % | C31: =(C30)/'Income Statement'!C7 -> 0.29746294 | D31: =(D30)/'Income Statement'!D7 -> 0.3166222 | E31: =(E30)/'Income Statement'!E7 -> 0.22090351 | F31: =(F30)/'Income Statement'!F7 -> -0.59596828 | G31: =(G30)/'Income Statement'!G7 -> -0.59711668 | H31: =(H30)/'Income Statement'!H7 -> -0.59515714

Sheet Dashboard
B1: FINANCIAL SUMMARY DASHBOARD
B2: Apple Inc. (AAPL) | USD ($mm) | FY End: September 30
B3: Key Metric | C3: FY2021A | D3: FY2022A | E3: FY2023A | F3: FY2024E | G3: FY2025E | H3: FY2026E
B4: INCOME STATEMENT SUMMARY
B5: Total Revenue | C5: ='Income Statement'!C7 -> 365817 | D5: ='Income Statement'!D7 -> 394328 | E5: ='Income Statement'!E7 -> 383285 | F5: ='Income Statement'!F7 -> 406577 | G5: ='Income Statement'!G7 -> 432356 | H5: ='Income Statement'!H7 -> 460632
B6: Gross Profit | C6: ='Income Statement'!C13 -> 152329 | D6: ='Income Statement'!D13 -> 171586 | E6: ='Income Statement'!E13 -> 169148 | F6: ='Income Statement'!F13 -> 35582.53 | G6: ='Income Statement'!G13 -> 40811.625 | H6: ='Income Statement'!H13 -> 46732.4
B7: Gross Margin % | C7: ='Income Statement'!C13/'Income Statement'!C7 -> 0.41640766 | D7: ='Income Statement'!D13/'Income Statement'!D7 -> 0.43513522 | E7: ='Income Statement'!E13/'Income Statement'!E7 -> 0.4413113 | F7: ='Income Statement'!F13/'Income Statement'!F7 -> 0.087517321 | G7: ='Income Statement'!G13/'Income Statement'!G7 -> 0.094393567 | H7: ='Income Statement'!H13/'Income Statement'!H7 -> 0.10145279
B8: EBIT (Operating Income) | C8: ='Income Statement'!C19 -> 108442 | D8: ='Income Statement'!D19 -> 120241 | E8: ='Income Statement'!E19 -> 114301 | F8: ='Income Statement'!F19 -> -295777.72 | G8: ='Income Statement'!G19 -> -315449.72 | H8: ='Income Statement'!H19 -> -334670.9
B9: EBIT Margin % | C9: ='Income Statement'!C19/'Income Statement'!C7 -> 0.29643784 | D9: ='Income Statement'!D19/'Income Statement'!D7 -> 0.30492636 | E9: ='Income Statement'!E19/'Income Statement'!E7 -> 0.29821412 | F9: ='Income Statement'!F19/'Income Statement'!F7 -> -0.72748268 | G9: ='Income Statement'!G19/'Income Statement'!G7 -> -0.72960643 | H9: ='Income Statement'!H19/'Income Statement'!H7 -> -0.72654721
B10: Net Income | C10: ='Income Statement'!C25 -> 94173 | D10: ='Income Statement'!D25 -> 100607 | E10: ='Income Statement'!E25 -> 83987 | F10: ='Income Statement'!F25 -> -251921.07 | G10: ='Income Statement'!G25 -> -268642.26 | H10: ='Income Statement'!H25 -> -284980.26
B11: Net Margin % | C11: ='Income Statement'!C25/'Income Statement'!C7 -> 0.25743199 | D11: ='Income Statement'!D25/'Income Statement'!D7 -> 0.25513532 | E11: ='Income Statement'!E25/'Income Statement'!E7 -> 0.21912415 | F11: ='Income Statement'!F25/'Income Statement'!F7 -> -0.61961465 | G11: ='Income Statement'!G25/'Income Statement'!G7 -> -0.62134505 | H11: ='Income Statement'!H25/'Income Statement'!H7 -> -0.61867231
B12: Diluted EPS | C12: ='Income Statement'!C29 -> 5.5842623 | D12: ='Income Statement'!D29 -> 6.2045637 | E12: ='Income Statement'!E29 -> 5.3345401 | F12: ='Income Statement'!F29 -> -16.907454 | G12: ='Income Statement'!G29 -> -18.274984 | H12: ='Income Statement'!H29 -> -19.653811
B13: CASH FLOW & BALANCE SHEET SUMMARY
B14: Free Cash Flow | C14: ='Cash Flow'!C13+'Cash Flow'!C15 -> 108817 | D14: ='Cash Flow'!D13+'Cash Flow'!D15 -> 124853 | E14: ='Cash Flow'!E13+'Cash Flow'!E15 -> 84669 | F14: ='Cash Flow'!F13+'Cash Flow'!F15 -> -242307 | G14: ='Cash Flow'!G13+'Cash Flow'!G15 -> -258166.98 | H14: ='Cash Flow'!H13+'Cash Flow'!H15 -> -274148.42
B15: FCF Margin % | C15: =('Cash Flow'!C13+'Cash Flow'!C15)/'Income Statement'!C7 -> 0.29746294 | D15: =('Cash Flow'!D13+'Cash Flow'!D15)/'Income Statement'!D7 -> 0.3166222 | E15: =('Cash Flow'!E13+'Cash Flow'!E15)/'Income Statement'!E7 -> 0.22090351 | F15: =('Cash Flow'!F13+'Cash Flow'!F15)/'Income Statement'!F7 -> -0.59596828 | G15: =('Cash Flow'!G13+'Cash Flow'!G15)/'Income Statement'!G7 -> -0.59711668 | H15: =('Cash Flow'!H13+'Cash Flow'!H15)/'Income Statement'!H7 -> -0.59515714
B16: Ending Cash | C16: ='Cash Flow'!C27 -> -4130 | D16: ='Cash Flow'!D27 -> 51011 | E16: ='Cash Flow'!E27 -> 5050 | F16: ='Cash Flow'!F27 -> -312842 | G16: ='Cash Flow'!G27 -> -358666.98 | H16: ='Cash Flow'!H27 -> -374648.42
B17: Total Assets | C17: ='Balance Sheet'!C17 -> 347061 | D17: ='Balance Sheet'!D17 -> 320007 | E17: ='Balance Sheet'!E17 -> 321106 | F17: ='Balance Sheet'!F17 -> 280092.37 | G17: ='Balance Sheet'!G17 -> 281528.7 | H17: ='Balance Sheet'!H17 -> 283127.82
B18: Total Debt (ST+LT) | C18: ='Balance Sheet'!C20+'Balance Sheet'!C25 -> 120275 | D18: ='Balance Sheet'!D20+'Balance Sheet'!D25 -> 120069 | E18: ='Balance Sheet'!E20+'Balance Sheet'!E25 -> 105103 | F18: ='Balance Sheet'!F20+'Balance Sheet'!F25 -> 100000 | G18: ='Balance Sheet'!G20+'Balance Sheet'!G25 -> 100000 | H18: ='Balance Sheet'!H20+'Balance Sheet'!H25 -> 100000
B19: Total Equity | C19: ='Balance Sheet'!C33 -> 61536 | D19: ='Balance Sheet'!D33 -> 50672 | E19: ='Balance Sheet'!E33 -> 62146 | F19: ='Balance Sheet'!F33 -> -177135.07 | G19: ='Balance Sheet'!G33 -> -440777.33 | H19: ='Balance Sheet'!H33 -> -720757.59
